{"data_repr": "percentile", "normalizer": "minmax", "DD": {"srs_type": "mot", "severity_group": ["sever", "TD"], "age_group": null, "divide_data": false, "balance": false}, "FS": {"est": ["lsvm", "rf", "lgbm", "lr", "xgb"], "cv": 5, "scoring": "balanced_accuracy", "n_jobs": -1, "verbose": 0, "step": 1, "min_features_to_select": 1}, "ML": {"est": ["lr", "lsvm", "svm", "lgbm", "rf", "ridge", "gnb", "nn"], "cv": 5, "scoring": "balanced_accuracy", "n_jobs": -1, "verbose": 0, "hyper_search_type": "random", "n_iter": 50}}